setup.py
jz/__init__.py
jz.stream.egg-info/PKG-INFO
jz.stream.egg-info/SOURCES.txt
jz.stream.egg-info/dependency_links.txt
jz.stream.egg-info/namespace_packages.txt
jz.stream.egg-info/requires.txt
jz.stream.egg-info/top_level.txt
jz/stream/__init__.py
jz/stream/browser.py
jz/stream/configure.zcml
jz/stream/interfaces.py
jz/stream/readme.txt
jz/stream/stream.py
jz/stream/tests/__init__.py
jz/stream/tests/sample.py
jz/stream/tests/test_browser.py
