Metadata-Version: 1.0
Name: jz.stream
Version: 0.1
Summary: Generic data stream classes and views.
Home-page: http://www.jellofishi.com/zope
Author: Gabi Shaar
Author-email: gabi@jbox-comp.com
License: GPL
Platform: UNKNOWN
